HackerGprat/__init__.py
HackerGprat/basic.py
HackerGprat/converter.py
HackerGprat/internet.py
HackerGprat/notification.py
HackerGprat/short_name.py
HackerGprat/test.py
HackerGprat/trading.py
HackerGprat/trading_indicator.py
HackerGprat/yt.py
HackerGprat-0.3.5.dist-info/LICENSE
HackerGprat-0.3.5.dist-info/METADATA
HackerGprat-0.3.5.dist-info/WHEEL
HackerGprat-0.3.5.dist-info/top_level.txt
HackerGprat-0.3.5.dist-info/RECORD
