Metadata-Version: 2.1
Name: HackerGprat
Version: 0.3.5
Summary: Here You can find Userfull fucntion which you need in your every python packages.
Home-page: https://github.com/HackerGprat/HackerGprat-PIP-Library/
Author: HackerGprat
Author-email: Sorry@gmail.com
Project-URL: Bug Tracker, https://github.com/HackerGprat/HackerGprat-PIP-Library/issues
Project-URL: Website, https://hackergprat.github.io
Project-URL: Instagram, https://instagram.com/HackerGprat
Project-URL: YouTube, https://youtube.com/HackerGprat
Classifier: Programming Language :: Python :: 3
Classifier: License :: OSI Approved :: MIT License
Classifier: Operating System :: OS Independent
Requires-Python: >=3.6
License-File: LICENSE
Requires-Dist: numpy
Requires-Dist: pandas
Requires-Dist: matplotlib
Requires-Dist: ipython
Requires-Dist: scipy
Requires-Dist: scikit-learn
Requires-Dist: seaborn
Requires-Dist: pillow
Requires-Dist: wheel
Requires-Dist: requests
Requires-Dist: bs4
Requires-Dist: plyer
Requires-Dist: binance
Requires-Dist: python-binance
Requires-Dist: setuptools
Requires-Dist: jupyterlab
Requires-Dist: jupyter
Requires-Dist: nltk
Requires-Dist: spacy
Requires-Dist: textblob
Requires-Dist: CoreNLP
Requires-Dist: docx
Requires-Dist: PyPDF2
Requires-Dist: build
